.bumpversion.cfg
.cookiecutterrc
.coveragerc
.editorconfig
AUTHORS.rst
CHANGELOG.rst
CONTRIBUTING.rst
LICENSE
MANIFEST.in
README.md
setup.cfg
setup.py
tox.ini
ci/bootstrap.py
docs/authors.rst
docs/changelog.rst
docs/conf.py
docs/contributing.rst
docs/index.rst
docs/installation.rst
docs/readme.rst
docs/requirements.txt
docs/spelling_wordlist.txt
docs/usage.rst
docs/reference/index.rst
docs/reference/snakespit.rst
src/snakespit/__init__.py
src/snakespit/__main__.py
src/snakespit/cli.py
src/snakespit.egg-info/PKG-INFO
src/snakespit.egg-info/SOURCES.txt
src/snakespit.egg-info/dependency_links.txt
src/snakespit.egg-info/entry_points.txt
src/snakespit.egg-info/not-zip-safe
src/snakespit.egg-info/requires.txt
src/snakespit.egg-info/top_level.txt
tests/test_snakespit.py